baanner_sooj1n/__init__.py
baanner_sooj1n/banner.py
baanner_sooj1n-0.3.0.dist-info/METADATA
baanner_sooj1n-0.3.0.dist-info/WHEEL
baanner_sooj1n-0.3.0.dist-info/entry_points.txt
baanner_sooj1n-0.3.0.dist-info/top_level.txt
baanner_sooj1n-0.3.0.dist-info/RECORD
