Metadata-Version: 2.1
Name: baanner_sooj1n
Version: 0.3.0
Summary: Default template for PDM package
Author-email: sooj1n <sujin19371@gmail.com>
License: MIT
Project-URL: Homepage, https://github.com/sooj1n/banner_sooj1n
Project-URL: Issues, https://github.com/sooj1n/banner_sooj1n/issues
Requires-Python: >=3.9
Requires-Dist: pyfiglet >=1.0.2
